fitrd/__init__.py
fitrd/fitrd.py
fitrd-0.1.6.dist-info/LICENSE
fitrd-0.1.6.dist-info/METADATA
fitrd-0.1.6.dist-info/WHEEL
fitrd-0.1.6.dist-info/top_level.txt
fitrd-0.1.6.dist-info/RECORD
