Metadata-Version: 2.1
Name: fitrd
Version: 0.1.6
Summary: Code to fit quasi-normal modes to ringdown waveforms
Home-page: https://github.com/halstonblim/EMRI_Ringdown_QNM_Fits
Author: Halston Lim
Author-email: hblim@mit.edu
License: UNKNOWN
Platform: UNKNOWN
Classifier: Programming Language :: Python :: 3
Classifier: License :: OSI Approved :: MIT License
Classifier: Operating System :: OS Independent
Requires-Python: <3.10,>=3.7
License-File: LICENSE
Requires-Dist: qnm
Requires-Dist: pandas
Requires-Dist: numpy
